<?xml version="1.0" encoding="utf-8"?>
<LanguageData>
  <!--The following translations were generated by https://www.deepl.com/-->
  <!-- EN: light alloy dining chair -->
  <PortableDiningChair.label>Leichtmetall-Esszimmerstuhl</PortableDiningChair.label>
  <!-- EN: A lightweight dining chair. Meant for eating at table while traveling. -->
  <PortableDiningChair.description>Ein leichter Esszimmerstuhl. Gedacht für das Essen am Tisch während der Reise.</PortableDiningChair.description>
  <!-- EN: light alloy hospital bed -->
  <PortableHospitalBed.label>Krankenhausbett aus Leichtmetall</PortableHospitalBed.label>
  <!-- EN: A lightweight bed specially designed for use while traveling. Adjustable for a patient and festooned with built-in equipment, it improves medical outcomes over normal beds. -->
  <PortableHospitalBed.description>Ein leichtes Bett, das speziell für die Verwendung auf Reisen entwickelt wurde. Es ist für einen Patienten einstellbar und mit eingebauten Geräten ausgestattet, die die medizinischen Ergebnisse gegenüber normalen Betten verbessern.</PortableHospitalBed.description>
  <!-- EN: light alloy table (1x2) -->
  <PortableTable1x2c.label>Leichtmetalltisch (1x2)</PortableTable1x2c.label>
  <!-- EN: People eat off tables when chairs are placed facing them. This table is lighter than a regular table of the same size. -->
  <PortableTable1x2c.description>Menschen essen von Tischen, wenn Stühle ihnen gegenüber gestellt werden. Dieser Tisch ist leichter als ein normaler Tisch der gleichen Größe.</PortableTable1x2c.description>
</LanguageData>
